setup.py
easypysql/__init__.py
easypysql/easy.py
easypysql/url.py
easypysql.egg-info/PKG-INFO
easypysql.egg-info/SOURCES.txt
easypysql.egg-info/dependency_links.txt
easypysql.egg-info/requires.txt
easypysql.egg-info/top_level.txt