Metadata-Version: 1.0
Name: easypysql
Version: 0.1.4
Summary: A simple and small python ORM framework
Home-page: https://github.com/Justin13wyx/easypysql
Author: Justin13
Author-email: justin13wyx@gmail.com
License: UNKNOWN
Platform: UNKNOWN
